nanslice/__init__.py
nanslice/box.py
nanslice/colorbar.py
nanslice/jupyter.py
nanslice/layer.py
nanslice/nanscroll.py
nanslice/nanslicer.py
nanslice/nanviewer.py
nanslice/nipype.py
nanslice/slice_func.py
nanslice/slicer.py
nanslice/util.py
nanslice-1.0.0.dist-info/LICENSE.txt
nanslice-1.0.0.dist-info/METADATA
nanslice-1.0.0.dist-info/WHEEL
nanslice-1.0.0.dist-info/entry_points.txt
nanslice-1.0.0.dist-info/top_level.txt
nanslice-1.0.0.dist-info/RECORD
