Metadata-Version: 2.1
Name: nanslice
Version: 1.0.0
Summary: Scripts to slice and display neuroimages (probably stored in nifti format)
Home-page: https://github.com/spinicist/nanslice
Author: Tobias Wood
Author-email: tobias@spinicist.org.uk
License: MPL
Keywords: neuroimaging nifti
Platform: UNKNOWN
Classifier: Topic :: Scientific/Engineering :: Visualization
Classifier: Programming Language :: Python :: 3
Requires-Python: >=3
Requires-Dist: matplotlib (>=3.2.0)
Requires-Dist: nibabel (>=2.0.0)
Requires-Dist: numpy (>=1.14.2)
Requires-Dist: scipy (>=1.1.0)
Requires-Dist: colorcet (>=2.0.0)
